{
    "title": "Interlinking Dynamics: Carbon Dioxide Emission's Impact on Global Warming and Subsequent Effects on Marine Ecosystems via Ocean Temperature Fluctuations and Nutrient Availability",
    "abstract": "This paper investigates the cascading effects of increased atmospheric carbon dioxide concentrations on global climate change and marine environments. Firstly, we explore how escalated carbon dioxide levels act as a primary driver for global warming, enhancing the greenhouse effect. We further delineate how this rise in global temperatures positively correlates with sea temperature increments. The study then examines the resulting inverse relationship between higher oceanic temperatures and nutrient runoff, proposing mechanisms by which thermal alterations may disrupt nutrient dispersal patterns in marine ecosystems. Additionally, our analysis reveals that overfishing not only depletes marine biota but also appears to inhibit nutrient runoff, further complicating nutrient availability in coastal waters. Multiple data sources, including satellite observations and in-situ oceanographic measurements, provide a comprehensive view of these interconnected dynamics. Our findings underscore the complex interdependencies between anthropogenic activities and marine environmental processes, highlighting crucial considerations for sustainable ocean management and climate change mitigation strategies.",
    "entities": [
        "Ocean temperatures",
        "Carbon dioxide levels",
        "Overfishing",
        "Global warming",
        "Nutrient Runoff"
    ],
    "relationship_types": [
        "cause",
        "negatively correlate",
        "positively correlate",
        "inhibit"
    ],
    "relationships": [
        {
            "entity_1": "Carbon dioxide levels",
            "entity_2": "Global warming",
            "relationship": "cause"
        },
        {
            "entity_1": "Global warming",
            "entity_2": "Ocean temperatures",
            "relationship": "cause"
        },
        {
            "entity_1": "Ocean temperatures",
            "entity_2": "Nutrient Runoff",
            "relationship": "negatively correlate"
        },
        {
            "entity_1": "Overfishing",
            "entity_2": "Nutrient Runoff",
            "relationship": "inhibit"
        },
        {
            "entity_1": "Carbon dioxide levels",
            "entity_2": "Ocean temperatures",
            "relationship": "positively correlate"
        }
    ]
}